nlator/__init__.py
nlator/nlator.py
nlator-1.0.dist-info/METADATA
nlator-1.0.dist-info/WHEEL
nlator-1.0.dist-info/top_level.txt
nlator-1.0.dist-info/RECORD
